{
  "config": {
    "dataset": "cifar100",
    "suite": "random-affine",
    "patch_size": 8,
    "depth": 3,
    "n_train": 2048,
    "n_test": 512,
    "batch_size": 256,
    "epochs": 20,
    "lr": 0.0003,
    "weight_decay": 0.05,
    "head_reg": 100.0,
    "lambda_reg": 1.0,
    "num_landmarks": 8,
    "num_heads": 4,
    "analytic_num_heads": 2,
    "mlp_ratio": 2.0,
    "attention_kind": "landmark",
    "attention_target": "mean",
    "attention_rank": 16,
    "local_sigma": 1.5,
    "attention_power_iters": 24,
    "attention_num_bags": 12,
    "attention_bag_fraction": 0.3,
    "attention_seed": -1,
    "seed": 7,
    "image_size": 32,
    "in_chans": 3
  },
  "attention_kinds": [
    "score-self-power-bagged-gain"
  ],
  "results": [
    {
      "model": "closed-form-transformer:score-self-power-bagged-gain",
      "config": {
        "dataset": "cifar100",
        "suite": "random-affine",
        "patch_size": 8,
        "depth": 3,
        "n_train": 2048,
        "n_test": 512,
        "batch_size": 256,
        "epochs": 20,
        "lr": 0.0003,
        "weight_decay": 0.05,
        "head_reg": 100.0,
        "lambda_reg": 1.0,
        "num_landmarks": 8,
        "num_heads": 4,
        "analytic_num_heads": 2,
        "mlp_ratio": 2.0,
        "attention_kind": "score-self-power-bagged-gain",
        "attention_target": "mean",
        "attention_rank": 16,
        "local_sigma": 1.5,
        "attention_power_iters": 24,
        "attention_num_bags": 12,
        "attention_bag_fraction": 0.3,
        "attention_seed": -1,
        "seed": 7,
        "image_size": 32,
        "in_chans": 3
      },
      "classifier_accuracy": 0.076171875,
      "layers": [
        {
          "depth": 1,
          "classifier_accuracy": 0.04296875,
          "attention_kind": "score-self-power-bagged-gain",
          "attention_rank": 16,
          "attention_mix_scale": 0.7690031663731073,
          "selected_score_scales": {
            "all": 1.0
          },
          "selected_prior_weight": null,
          "train_fit_loss": 0.02074498983653078,
          "top_shared_eigenvalue": 0.9998749896579547
        },
        {
          "depth": 2,
          "classifier_accuracy": 0.072265625,
          "attention_kind": "score-self-power-bagged-gain",
          "attention_rank": 16,
          "attention_mix_scale": 0.7059787251518874,
          "selected_score_scales": {
            "all": 6.0
          },
          "selected_prior_weight": null,
          "train_fit_loss": 0.07136211949166371,
          "top_shared_eigenvalue": 0.9950488665172229
        },
        {
          "depth": 3,
          "classifier_accuracy": 0.076171875,
          "attention_kind": "score-self-power-bagged-gain",
          "attention_rank": 16,
          "attention_mix_scale": 0.7557376121864824,
          "selected_score_scales": {
            "all": 6.0
          },
          "selected_prior_weight": null,
          "train_fit_loss": 0.09797806979790893,
          "top_shared_eigenvalue": 0.9895412338709093
        }
      ],
      "output_param_count": 57600,
      "hidden_param_count": 451584,
      "total_parameter_count": 509184,
      "fit_time_sec": 129.18398370000068
    }
  ]
}