{
  "dataset": "cifar10",
  "suite": "single-translation",
  "lambda": 0.3,
  "depth": 3,
  "final_dim": 32,
  "n_train": 6000,
  "n_test": 1000,
  "full_probe_accuracy": 0.284,
  "final_pca_probe_accuracy": 0.327,
  "raw_input_pca_probe_accuracy": 0.375,
  "layers": [
    {
      "layer": 1,
      "distance_to_identity": 140.50720704981433,
      "distance_to_whitened_identity": 31.06134164658679,
      "total_delta_trace": 84.2249254175536,
      "post_delta_trace": 1478.4841027802509,
      "post_shared_trace": 2250.7684551604834,
      "base_trace": 3230.6677165915467,
      "max_whitened_delta": 3.6924174565598973
    },
    {
      "layer": 2,
      "distance_to_identity": 124.24651762071417,
      "distance_to_whitened_identity": 36.811641214866206,
      "total_delta_trace": 1478.4841027802509,
      "post_delta_trace": 1829.4519458616876,
      "post_shared_trace": 2090.138842757012,
      "base_trace": 3199.616383519514,
      "max_whitened_delta": 3.649588282386765
    },
    {
      "layer": 3,
      "distance_to_identity": 220.56187538814726,
      "distance_to_whitened_identity": 36.83574331707637,
      "total_delta_trace": 1829.4519458616876,
      "post_delta_trace": 2354.766212029146,
      "post_shared_trace": 1844.2529437718974,
      "base_trace": 3166.390624626588,
      "max_whitened_delta": 3.6753119998637462
    }
  ]
}